Workbook
Name defense: DEF!$B$2:$B$27
Name dlkp: 'Player Lookup'!$A$2:$D$23
Name flex: FLEX!$B$2:$B$708
Name flkp: 'Player Lookup'!$A$24:$D$38
Name nickname: Players!$B$2:$B$834
Name playerlkp: 'Player Lookup'!$A$2:$D$834
Name Players: Players!$A$2:$E$834
Name qb: QB!$B$2:$B$101
Name qblkp: QB!$A$2:$E$101
Name rb: RB!$B$2:$B$181
Name rblkp: 'Player Lookup'!$A$61:$D$70
Name te: TE!$B$2:$B$179
Name telkp: 'Player Lookup'!$A$71:$D$80
Name wr: WR!$B$2:$B$350
Name wrlkp: 'Player Lookup'!$A$81:$D$95

Sheet Teams
A1: POSITION | B1: PLAYER | C1: SALARY | D1: AVG | E1: INJ | G1: PLAYER | H1: SALARY | I1: AVG | J1: INJ | L1: PLAYER | M1: SALARY | N1: AVG | O1: INJ
A2: QB | B2: Justin Herbert | C2: =IFERROR(IF(INDEX(Players,MATCH(B2,nickname,0),MATCH($C$1,Players!$1:$1,0))=0,"",INDEX(Players,MATCH(B2,nickname,0),MATCH($C$1,Players!$1:$1,0))),"") -> 7600 | D2: =IFERROR(IF(INDEX(Players,MATCH(B2,nickname,0),MATCH($D$1,Players!$1:$1,0))=0,"",INDEX(Players,MATCH(B2,nickname,0),MATCH($D$1,Players!$1:$1,0))),"") -> 18.512308 | E2: =IFERROR(IF(VLOOKUP(B2,playerlkp,3,0)=0,"",VLOOKUP(B2,playerlkp,3,0)),"") | G2: Justin Herbert | H2: =IFERROR(IF(INDEX(Players,MATCH(G2,nickname,0),MATCH($C$1,Players!$1:$1,0))=0,"",INDEX(Players,MATCH(G2,nickname,0),MATCH($C$1,Players!$1:$1,0))),"") -> 7600 | I2: =IFERROR(IF(INDEX(Players,MATCH(G2,nickname,0),MATCH($D$1,Players!$1:$1,0))=0,"",INDEX(Players,MATCH(G2,nickname,0),MATCH($D$1,Players!$1:$1,0))),"") -> 18.512308 | J2: =IFERROR(IF(VLOOKUP(G2,playerlkp,3,0)=0,"",VLOOKUP(G2,playerlkp,3,0)),"") | L2: Baker Mayfield | M2: =IFERROR(IF(INDEX(Players,MATCH(L2,nickname,0),MATCH($C$1,Players!$1:$1,0))=0,"",INDEX(Players,MATCH(L2,nickname,0),MATCH($C$1,Players!$1:$1,0))),"") -> 7200 | N2: =IFERROR(IF(INDEX(Players,MATCH(L2,nickname,0),MATCH($D$1,Players!$1:$1,0))=0,"",INDEX(Players,MATCH(L2,nickname,0),MATCH($D$1,Players!$1:$1,0))),"") -> 17.71579 | O2: =IFERROR(IF(VLOOKUP(L2,playerlkp,3,0)=0,"",VLOOKUP(L2,playerlkp,3,0)),"")
A3: RB1 | B3: Raheem Mostert | C3: =IFERROR(IF(INDEX(Players,MATCH(B3,nickname,0),MATCH($C$1,Players!$1:$1,0))=0,"",INDEX(Players,MATCH(B3,nickname,0),MATCH($C$1,Players!$1:$1,0))),"") -> 6600 | D3: =IFERROR(IF(INDEX(Players,MATCH(B3,nickname,0),MATCH($D$1,Players!$1:$1,0))=0,"",INDEX(Players,MATCH(B3,nickname,0),MATCH($D$1,Players!$1:$1,0))),"") -> 16.168751 | E3: =IFERROR(IF(VLOOKUP(B3,playerlkp,3,0)=0,"",VLOOKUP(B3,playerlkp,3,0)),"") | G3: Jahmyr Gibbs | H3: =IFERROR(IF(INDEX(Players,MATCH(G3,nickname,0),MATCH($C$1,Players!$1:$1,0))=0,"",INDEX(Players,MATCH(G3,nickname,0),MATCH($C$1,Players!$1:$1,0))),"") -> 8000 | I3: =IFERROR(IF(INDEX(Players,MATCH(G3,nickname,0),MATCH($D$1,Players!$1:$1,0))=0,"",INDEX(Players,MATCH(G3,nickname,0),MATCH($D$1,Players!$1:$1,0))),"") -> 14.522222 | J3: =IFERROR(IF(VLOOKUP(G3,playerlkp,3,0)=0,"",VLOOKUP(G3,playerlkp,3,0)),"") | L3: Raheem Mostert | M3: =IFERROR(IF(INDEX(Players,MATCH(L3,nickname,0),MATCH($C$1,Players!$1:$1,0))=0,"",INDEX(Players,MATCH(L3,nickname,0),MATCH($C$1,Players!$1:$1,0))),"") -> 6600 | N3: =IFERROR(IF(INDEX(Players,MATCH(L3,nickname,0),MATCH($D$1,Players!$1:$1,0))=0,"",INDEX(Players,MATCH(L3,nickname,0),MATCH($D$1,Players!$1:$1,0))),"") -> 16.168751 | O3: =IFERROR(IF(VLOOKUP(L3,playerlkp,3,0)=0,"",VLOOKUP(L3,playerlkp,3,0)),"")
A4: RB2 | B4: David Montgomery | C4: =IFERROR(IF(INDEX(Players,MATCH(B4,nickname,0),MATCH($C$1,Players!$1:$1,0))=0,"",INDEX(Players,MATCH(B4,nickname,0),MATCH($C$1,Players!$1:$1,0))),"") -> 7000 | D4: =IFERROR(IF(INDEX(Players,MATCH(B4,nickname,0),MATCH($D$1,Players!$1:$1,0))=0,"",INDEX(Players,MATCH(B4,nickname,0),MATCH($D$1,Players!$1:$1,0))),"") -> 13.166667 | E4: =IFERROR(IF(VLOOKUP(B4,playerlkp,3,0)=0,"",VLOOKUP(B4,playerlkp,3,0)),"") | G4: James Cook | H4: =IFERROR(IF(INDEX(Players,MATCH(G4,nickname,0),MATCH($C$1,Players!$1:$1,0))=0,"",INDEX(Players,MATCH(G4,nickname,0),MATCH($C$1,Players!$1:$1,0))),"") -> 7600 | I4: =IFERROR(IF(INDEX(Players,MATCH(G4,nickname,0),MATCH($D$1,Players!$1:$1,0))=0,"",INDEX(Players,MATCH(G4,nickname,0),MATCH($D$1,Players!$1:$1,0))),"") -> 12.173684 | J4: =IFERROR(IF(VLOOKUP(G4,playerlkp,3,0)=0,"",VLOOKUP(G4,playerlkp,3,0)),"") | L4: Jahmyr Gibbs | M4: =IFERROR(IF(INDEX(Players,MATCH(L4,nickname,0),MATCH($C$1,Players!$1:$1,0))=0,"",INDEX(Players,MATCH(L4,nickname,0),MATCH($C$1,Players!$1:$1,0))),"") -> 8000 | N4: =IFERROR(IF(INDEX(Players,MATCH(L4,nickname,0),MATCH($D$1,Players!$1:$1,0))=0,"",INDEX(Players,MATCH(L4,nickname,0),MATCH($D$1,Players!$1:$1,0))),"") -> 14.522222 | O4: =IFERROR(IF(VLOOKUP(L4,playerlkp,3,0)=0,"",VLOOKUP(L4,playerlkp,3,0)),"")
A5: WR1 | B5: Puka Nacua | C5: =IFERROR(IF(INDEX(Players,MATCH(B5,nickname,0),MATCH($C$1,Players!$1:$1,0))=0,"",INDEX(Players,MATCH(B5,nickname,0),MATCH($C$1,Players!$1:$1,0))),"") -> 8400 | D5: =IFERROR(IF(INDEX(Players,MATCH(B5,nickname,0),MATCH($D$1,Players!$1:$1,0))=0,"",INDEX(Players,MATCH(B5,nickname,0),MATCH($D$1,Players!$1:$1,0))),"") -> 15.244444 | E5: =IFERROR(IF(VLOOKUP(B5,playerlkp,3,0)=0,"",VLOOKUP(B5,playerlkp,3,0)),"") | G5: Puka Nacua | H5: =IFERROR(IF(INDEX(Players,MATCH(G5,nickname,0),MATCH($C$1,Players!$1:$1,0))=0,"",INDEX(Players,MATCH(G5,nickname,0),MATCH($C$1,Players!$1:$1,0))),"") -> 8400 | I5: =IFERROR(IF(INDEX(Players,MATCH(G5,nickname,0),MATCH($D$1,Players!$1:$1,0))=0,"",INDEX(Players,MATCH(G5,nickname,0),MATCH($D$1,Players!$1:$1,0))),"") -> 15.244444 | J5: =IFERROR(IF(VLOOKUP(G5,playerlkp,3,0)=0,"",VLOOKUP(G5,playerlkp,3,0)),"") | L5: Tyreek Hill | M5: =IFERROR(IF(INDEX(Players,MATCH(L5,nickname,0),MATCH($C$1,Players!$1:$1,0))=0,"",INDEX(Players,MATCH(L5,nickname,0),MATCH($C$1,Players!$1:$1,0))),"") -> 9600 | N5: =IFERROR(IF(INDEX(Players,MATCH(L5,nickname,0),MATCH($D$1,Players!$1:$1,0))=0,"",INDEX(Players,MATCH(L5,nickname,0),MATCH($D$1,Players!$1:$1,0))),"") -> 19.505883 | O5: =IFERROR(IF(VLOOKUP(L5,playerlkp,3,0)=0,"",VLOOKUP(L5,playerlkp,3,0)),"")
A6: WR2 | B6: Khalil Shakir | C6: =IFERROR(IF(INDEX(Players,MATCH(B6,nickname,0),MATCH($C$1,Players!$1:$1,0))=0,"",INDEX(Players,MATCH(B6,nickname,0),MATCH($C$1,Players!$1:$1,0))),"") -> 5400 | D6: =IFERROR(IF(INDEX(Players,MATCH(B6,nickname,0),MATCH($D$1,Players!$1:$1,0))=0,"",INDEX(Players,MATCH(B6,nickname,0),MATCH($D$1,Players!$1:$1,0))),"") -> 6.561111 | E6: =IFERROR(IF(VLOOKUP(B6,playerlkp,3,0)=0,"",VLOOKUP(B6,playerlkp,3,0)),"") | G6: Tank Dell | H6: =IFERROR(IF(INDEX(Players,MATCH(G6,nickname,0),MATCH($C$1,Players!$1:$1,0))=0,"",INDEX(Players,MATCH(G6,nickname,0),MATCH($C$1,Players!$1:$1,0))),"") -> 6400 | I6: =IFERROR(IF(INDEX(Players,MATCH(G6,nickname,0),MATCH($D$1,Players!$1:$1,0))=0,"",INDEX(Players,MATCH(G6,nickname,0),MATCH($D$1,Players!$1:$1,0))),"") -> 14.15 | J6: =IFERROR(IF(VLOOKUP(G6,playerlkp,3,0)=0,"",VLOOKUP(G6,playerlkp,3,0)),"") | M6: =IFERROR(IF(INDEX(Players,MATCH(L6,nickname,0),MATCH($C$1,Players!$1:$1,0))=0,"",INDEX(Players,MATCH(L6,nickname,0),MATCH($C$1,Players!$1:$1,0))),"") | N6: =IFERROR(IF(INDEX(Players,MATCH(L6,nickname,0),MATCH($D$1,Players!$1:$1,0))=0,"",INDEX(Players,MATCH(L6,nickname,0),MATCH($D$1,Players!$1:$1,0))),"") | O6: =IFERROR(IF(VLOOKUP(L6,playerlkp,3,0)=0,"",VLOOKUP(L6,playerlkp,3,0)),"")
A7: WR3 | B7: Nico Collins | C7: =IFERROR(IF(INDEX(Players,MATCH(B7,nickname,0),MATCH($C$1,Players!$1:$1,0))=0,"",INDEX(Players,MATCH(B7,nickname,0),MATCH($C$1,Players!$1:$1,0))),"") -> 7100 | D7: =IFERROR(IF(INDEX(Players,MATCH(B7,nickname,0),MATCH($D$1,Players!$1:$1,0))=0,"",INDEX(Players,MATCH(B7,nickname,0),MATCH($D$1,Players!$1:$1,0))),"") -> 13.816666 | E7: =IFERROR(IF(VLOOKUP(B7,playerlkp,3,0)=0,"",VLOOKUP(B7,playerlkp,3,0)),"") | G7: Stefon Diggs | H7: =IFERROR(IF(INDEX(Players,MATCH(G7,nickname,0),MATCH($C$1,Players!$1:$1,0))=0,"",INDEX(Players,MATCH(G7,nickname,0),MATCH($C$1,Players!$1:$1,0))),"") -> 6800 | I7: =IFERROR(IF(INDEX(Players,MATCH(G7,nickname,0),MATCH($D$1,Players!$1:$1,0))=0,"",INDEX(Players,MATCH(G7,nickname,0),MATCH($D$1,Players!$1:$1,0))),"") -> 12.278948 | J7: =IFERROR(IF(VLOOKUP(G7,playerlkp,3,0)=0,"",VLOOKUP(G7,playerlkp,3,0)),"") | M7: =IFERROR(IF(INDEX(Players,MATCH(L7,nickname,0),MATCH($C$1,Players!$1:$1,0))=0,"",INDEX(Players,MATCH(L7,nickname,0),MATCH($C$1,Players!$1:$1,0))),"") | N7: =IFERROR(IF(INDEX(Players,MATCH(L7,nickname,0),MATCH($D$1,Players!$1:$1,0))=0,"",INDEX(Players,MATCH(L7,nickname,0),MATCH($D$1,Players!$1:$1,0))),"") | O7: =IFERROR(IF(VLOOKUP(L7,playerlkp,3,0)=0,"",VLOOKUP(L7,playerlkp,3,0)),"")
A8: TE | B8: Cade Otton | C8: =IFERROR(IF(INDEX(Players,MATCH(B8,nickname,0),MATCH($C$1,Players!$1:$1,0))=0,"",INDEX(Players,MATCH(B8,nickname,0),MATCH($C$1,Players!$1:$1,0))),"") -> 5200 | D8: =IFERROR(IF(INDEX(Players,MATCH(B8,nickname,0),MATCH($D$1,Players!$1:$1,0))=0,"",INDEX(Players,MATCH(B8,nickname,0),MATCH($D$1,Players!$1:$1,0))),"") -> 6.7166668 | E8: =IFERROR(IF(VLOOKUP(B8,playerlkp,3,0)=0,"",VLOOKUP(B8,playerlkp,3,0)),"") | G8: Jake Ferguson | H8: =IFERROR(IF(INDEX(Players,MATCH(G8,nickname,0),MATCH($C$1,Players!$1:$1,0))=0,"",INDEX(Players,MATCH(G8,nickname,0),MATCH($C$1,Players!$1:$1,0))),"") -> 6000 | I8: =IFERROR(IF(INDEX(Players,MATCH(G8,nickname,0),MATCH($D$1,Players!$1:$1,0))=0,"",INDEX(Players,MATCH(G8,nickname,0),MATCH($D$1,Players!$1:$1,0))),"") -> 9.6611108 | J8: =IFERROR(IF(VLOOKUP(G8,playerlkp,3,0)=0,"",VLOOKUP(G8,playerlkp,3,0)),"") | M8: =IFERROR(IF(INDEX(Players,MATCH(L8,nickname,0),MATCH($C$1,Players!$1:$1,0))=0,"",INDEX(Players,MATCH(L8,nickname,0),MATCH($C$1,Players!$1:$1,0))),"") | N8: =IFERROR(IF(INDEX(Players,MATCH(L8,nickname,0),MATCH($D$1,Players!$1:$1,0))=0,"",INDEX(Players,MATCH(L8,nickname,0),MATCH($D$1,Players!$1:$1,0))),"") | O8: =IFERROR(IF(VLOOKUP(L8,playerlkp,3,0)=0,"",VLOOKUP(L8,playerlkp,3,0)),"")
A9: FLEX | B9: Kyren Williams | C9: =IFERROR(IF(INDEX(Players,MATCH(B9,nickname,0),MATCH($C$1,Players!$1:$1,0))=0,"",INDEX(Players,MATCH(B9,nickname,0),MATCH($C$1,Players!$1:$1,0))),"") -> 7800 | D9: =IFERROR(IF(INDEX(Players,MATCH(B9,nickname,0),MATCH($D$1,Players!$1:$1,0))=0,"",INDEX(Players,MATCH(B9,nickname,0),MATCH($D$1,Players!$1:$1,0))),"") -> 18.961538 | E9: =IFERROR(IF(VLOOKUP(B9,playerlkp,3,0)=0,"",VLOOKUP(B9,playerlkp,3,0)),"") | G9: David Montgomery | H9: =IFERROR(IF(INDEX(Players,MATCH(G9,nickname,0),MATCH($C$1,Players!$1:$1,0))=0,"",INDEX(Players,MATCH(G9,nickname,0),MATCH($C$1,Players!$1:$1,0))),"") -> 7000 | I9: =IFERROR(IF(INDEX(Players,MATCH(G9,nickname,0),MATCH($D$1,Players!$1:$1,0))=0,"",INDEX(Players,MATCH(G9,nickname,0),MATCH($D$1,Players!$1:$1,0))),"") -> 13.166667 | J9: =IFERROR(IF(VLOOKUP(G9,playerlkp,3,0)=0,"",VLOOKUP(G9,playerlkp,3,0)),"") | M9: =IFERROR(IF(INDEX(Players,MATCH(L9,nickname,0),MATCH($C$1,Players!$1:$1,0))=0,"",INDEX(Players,MATCH(L9,nickname,0),MATCH($C$1,Players!$1:$1,0))),"") | N9: =IFERROR(IF(INDEX(Players,MATCH(L9,nickname,0),MATCH($D$1,Players!$1:$1,0))=0,"",INDEX(Players,MATCH(L9,nickname,0),MATCH($D$1,Players!$1:$1,0))),"") | O9: =IFERROR(IF(VLOOKUP(L9,playerlkp,3,0)=0,"",VLOOKUP(L9,playerlkp,3,0)),"")
A10: DEF | B10: DAL | C10: =IFERROR(IF(INDEX(Players,MATCH(B10,nickname,0),MATCH($C$1,Players!$1:$1,0))=0,"",INDEX(Players,MATCH(B10,nickname,0),MATCH($C$1,Players!$1:$1,0))),"") -> 4500 | D10: =IFERROR(IF(INDEX(Players,MATCH(B10,nickname,0),MATCH($D$1,Players!$1:$1,0))=0,"",INDEX(Players,MATCH(B10,nickname,0),MATCH($D$1,Players!$1:$1,0))),"") -> 9.6666667 | E10: =IFERROR(IF(INDEX(Players,MATCH(B10,nickname,0),MATCH($E$1,Players!$1:$1,0))=0,"",INDEX(Players,MATCH(B10,nickname,0),MATCH($E$1,Players!$1:$1,0))), "") | G10: NE | H10: =IFERROR(IF(INDEX(Players,MATCH(G10,nickname,0),MATCH($C$1,Players!$1:$1,0))=0,"",INDEX(Players,MATCH(G10,nickname,0),MATCH($C$1,Players!$1:$1,0))),"") -> 3100 | I10: =IFERROR(IF(INDEX(Players,MATCH(G10,nickname,0),MATCH($D$1,Players!$1:$1,0))=0,"",INDEX(Players,MATCH(G10,nickname,0),MATCH($D$1,Players!$1:$1,0))),"") -> 6.4705882 | J10: =IFERROR(IF(INDEX(Players,MATCH(G10,nickname,0),MATCH($E$1,Players!$1:$1,0))=0,"",INDEX(Players,MATCH(G10,nickname,0),MATCH($E$1,Players!$1:$1,0))), "") | M10: =IFERROR(IF(INDEX(Players,MATCH(L10,nickname,0),MATCH($C$1,Players!$1:$1,0))=0,"",INDEX(Players,MATCH(L10,nickname,0),MATCH($C$1,Players!$1:$1,0))),"") | N10: =IFERROR(IF(INDEX(Players,MATCH(L10,nickname,0),MATCH($D$1,Players!$1:$1,0))=0,"",INDEX(Players,MATCH(L10,nickname,0),MATCH($D$1,Players!$1:$1,0))),"") | O10: =IFERROR(IF(INDEX(Players,MATCH(L10,nickname,0),MATCH($E$1,Players!$1:$1,0))=0,"",INDEX(Players,MATCH(L10,nickname,0),MATCH($E$1,Players!$1:$1,0))), "")
A11: TOTALS | C11: =60000-SUM(C2:C10) -> 400 | D11: =SUM(D2:D10) -> 118.81482 | H11: =60000-SUM(H2:H10) -> -900 | I11: =SUM(I2:I10) -> 116.17997 | M11: =60000-SUM(M2:M10) -> 28600 | N11: =SUM(N2:N10) -> 67.912645
B13: PLAYER | C13: SALARY | D13: AVG | E13: INJ | G13: PLAYER | H13: SALARY | I13: AVG | J13: INJ | L13: PLAYER | M13: SALARY | N13: AVG | O13: INJ
A14: QB | B14: Jared Goff | C14: =IFERROR(IF(INDEX(Players,MATCH(B14,nickname,0),MATCH($C$1,Players!$1:$1,0))=0,"",INDEX(Players,MATCH(B14,nickname,0),MATCH($C$1,Players!$1:$1,0))),"") -> 7500 | D14: =IFERROR(IF(INDEX(Players,MATCH(B14,nickname,0),MATCH($D$1,Players!$1:$1,0))=0,"",INDEX(Players,MATCH(B14,nickname,0),MATCH($D$1,Players!$1:$1,0))),"") -> 17.544 | E14: =IFERROR(IF(VLOOKUP(B14,playerlkp,3,0)=0,"",VLOOKUP(B14,playerlkp,3,0)),"") | G14: Baker Mayfield | H14: =IFERROR(IF(INDEX(Players,MATCH(G14,nickname,0),MATCH($C$1,Players!$1:$1,0))=0,"",INDEX(Players,MATCH(G14,nickname,0),MATCH($C$1,Players!$1:$1,0))),"") -> 7200 | I14: =IFERROR(IF(INDEX(Players,MATCH(G14,nickname,0),MATCH($D$1,Players!$1:$1,0))=0,"",INDEX(Players,MATCH(G14,nickname,0),MATCH($D$1,Players!$1:$1,0))),"") -> 17.71579 | J14: =IFERROR(IF(VLOOKUP(G14,playerlkp,3,0)=0,"",VLOOKUP(G14,playerlkp,3,0)),"") | L14: Josh Allen | M14: =IFERROR(IF(INDEX(Players,MATCH(L14,nickname,0),MATCH($C$1,Players!$1:$1,0))=0,"",INDEX(Players,MATCH(L14,nickname,0),MATCH($C$1,Players!$1:$1,0))),"") -> 9200 | N14: =IFERROR(IF(INDEX(Players,MATCH(L14,nickname,0),MATCH($D$1,Players!$1:$1,0))=0,"",INDEX(Players,MATCH(L14,nickname,0),MATCH($D$1,Players!$1:$1,0))),"") -> 24.989473 | O14: =IFERROR(IF(VLOOKUP(L14,playerlkp,3,0)=0,"",VLOOKUP(L14,playerlkp,3,0)),"")
A15: RB1 | B15: David Montgomery | C15: =IFERROR(IF(INDEX(Players,MATCH(B15,nickname,0),MATCH($C$1,Players!$1:$1,0))=0,"",INDEX(Players,MATCH(B15,nickname,0),MATCH($C$1,Players!$1:$1,0))),"") -> 7000 | D15: =IFERROR(IF(INDEX(Players,MATCH(B15,nickname,0),MATCH($D$1,Players!$1:$1,0))=0,"",INDEX(Players,MATCH(B15,nickname,0),MATCH($D$1,Players!$1:$1,0))),"") -> 13.166667 | E15: =IFERROR(IF(VLOOKUP(B15,playerlkp,3,0)=0,"",VLOOKUP(B15,playerlkp,3,0)),"") | G15: Bijan Robinson | H15: =IFERROR(IF(INDEX(Players,MATCH(G15,nickname,0),MATCH($C$1,Players!$1:$1,0))=0,"",INDEX(Players,MATCH(G15,nickname,0),MATCH($C$1,Players!$1:$1,0))),"") -> 8800 | I15: =IFERROR(IF(INDEX(Players,MATCH(G15,nickname,0),MATCH($D$1,Players!$1:$1,0))=0,"",INDEX(Players,MATCH(G15,nickname,0),MATCH($D$1,Players!$1:$1,0))),"") -> 12.782353 | J15: =IFERROR(IF(VLOOKUP(G15,playerlkp,3,0)=0,"",VLOOKUP(G15,playerlkp,3,0)),"") | L15: Bijan Robinson | M15: =IFERROR(IF(INDEX(Players,MATCH(L15,nickname,0),MATCH($C$1,Players!$1:$1,0))=0,"",INDEX(Players,MATCH(L15,nickname,0),MATCH($C$1,Players!$1:$1,0))),"") -> 8800 | N15: =IFERROR(IF(INDEX(Players,MATCH(L15,nickname,0),MATCH($D$1,Players!$1:$1,0))=0,"",INDEX(Players,MATCH(L15,nickname,0),MATCH($D$1,Players!$1:$1,0))),"") -> 12.782353 | O15: =IFERROR(IF(VLOOKUP(L15,playerlkp,3,0)=0,"",VLOOKUP(L15,playerlkp,3,0)),"")
A16: RB2 | B16: Jahmyr Gibbs | C16: =IFERROR(IF(INDEX(Players,MATCH(B16,nickname,0),MATCH($C$1,Players!$1:$1,0))=0,"",INDEX(Players,MATCH(B16,nickname,0),MATCH($C$1,Players!$1:$1,0))),"") -> 8000 | D16: =IFERROR(IF(INDEX(Players,MATCH(B16,nickname,0),MATCH($D$1,Players!$1:$1,0))=0,"",INDEX(Players,MATCH(B16,nickname,0),MATCH($D$1,Players!$1:$1,0))),"") -> 14.522222 | E16: =IFERROR(IF(VLOOKUP(B16,playerlkp,3,0)=0,"",VLOOKUP(B16,playerlkp,3,0)),"") | G16: Jahmyr Gibbs | H16: =IFERROR(IF(INDEX(Players,MATCH(G16,nickname,0),MATCH($C$1,Players!$1:$1,0))=0,"",INDEX(Players,MATCH(G16,nickname,0),MATCH($C$1,Players!$1:$1,0))),"") -> 8000 | I16: =IFERROR(IF(INDEX(Players,MATCH(G16,nickname,0),MATCH($D$1,Players!$1:$1,0))=0,"",INDEX(Players,MATCH(G16,nickname,0),MATCH($D$1,Players!$1:$1,0))),"") -> 14.522222 | J16: =IFERROR(IF(VLOOKUP(G16,playerlkp,3,0)=0,"",VLOOKUP(G16,playerlkp,3,0)),"") | L16: Bijan Robinson | M16: =IFERROR(IF(INDEX(Players,MATCH(L16,nickname,0),MATCH($C$1,Players!$1:$1,0))=0,"",INDEX(Players,MATCH(L16,nickname,0),MATCH($C$1,Players!$1:$1,0))),"") -> 8800 | N16: =IFERROR(IF(INDEX(Players,MATCH(L16,nickname,0),MATCH($D$1,Players!$1:$1,0))=0,"",INDEX(Players,MATCH(L16,nickname,0),MATCH($D$1,Players!$1:$1,0))),"") -> 12.782353 | O16: =IFERROR(IF(VLOOKUP(L16,playerlkp,3,0)=0,"",VLOOKUP(L16,playerlkp,3,0)),"")
A17: WR1 | C17: =IFERROR(IF(INDEX(Players,MATCH(B17,nickname,0),MATCH($C$1,Players!$1:$1,0))=0,"",INDEX(Players,MATCH(B17,nickname,0),MATCH($C$1,Players!$1:$1,0))),"") | D17: =IFERROR(IF(INDEX(Players,MATCH(B17,nickname,0),MATCH($D$1,Players!$1:$1,0))=0,"",INDEX(Players,MATCH(B17,nickname,0),MATCH($D$1,Players!$1:$1,0))),"") | E17: =IFERROR(IF(VLOOKUP(B17,playerlkp,3,0)=0,"",VLOOKUP(B17,playerlkp,3,0)),"") | H17: =IFERROR(IF(INDEX(Players,MATCH(G17,nickname,0),MATCH($C$1,Players!$1:$1,0))=0,"",INDEX(Players,MATCH(G17,nickname,0),MATCH($C$1,Players!$1:$1,0))),"") | I17: =IFERROR(IF(INDEX(Players,MATCH(G17,nickname,0),MATCH($D$1,Players!$1:$1,0))=0,"",INDEX(Players,MATCH(G17,nickname,0),MATCH($D$1,Players!$1:$1,0))),"") | J17: =IFERROR(IF(VLOOKUP(G17,playerlkp,3,0)=0,"",VLOOKUP(G17,playerlkp,3,0)),"") | L17: Tyreek Hill | M17: =IFERROR(IF(INDEX(Players,MATCH(L17,nickname,0),MATCH($C$1,Players!$1:$1,0))=0,"",INDEX(Players,MATCH(L17,nickname,0),MATCH($C$1,Players!$1:$1,0))),"") -> 9600 | N17: =IFERROR(IF(INDEX(Players,MATCH(L17,nickname,0),MATCH($D$1,Players!$1:$1,0))=0,"",INDEX(Players,MATCH(L17,nickname,0),MATCH($D$1,Players!$1:$1,0))),"") -> 19.505883 | O17: =IFERROR(IF(VLOOKUP(L17,playerlkp,3,0)=0,"",VLOOKUP(L17,playerlkp,3,0)),"")
A18: WR2 | C18: =IFERROR(IF(INDEX(Players,MATCH(B18,nickname,0),MATCH($C$1,Players!$1:$1,0))=0,"",INDEX(Players,MATCH(B18,nickname,0),MATCH($C$1,Players!$1:$1,0))),"") | D18: =IFERROR(IF(INDEX(Players,MATCH(B18,nickname,0),MATCH($D$1,Players!$1:$1,0))=0,"",INDEX(Players,MATCH(B18,nickname,0),MATCH($D$1,Players!$1:$1,0))),"") | E18: =IFERROR(IF(VLOOKUP(B18,playerlkp,3,0)=0,"",VLOOKUP(B18,playerlkp,3,0)),"") | G18: Tyreek Hill | H18: =IFERROR(IF(INDEX(Players,MATCH(G18,nickname,0),MATCH($C$1,Players!$1:$1,0))=0,"",INDEX(Players,MATCH(G18,nickname,0),MATCH($C$1,Players!$1:$1,0))),"") -> 9600 | I18: =IFERROR(IF(INDEX(Players,MATCH(G18,nickname,0),MATCH($D$1,Players!$1:$1,0))=0,"",INDEX(Players,MATCH(G18,nickname,0),MATCH($D$1,Players!$1:$1,0))),"") -> 19.505883 | J18: =IFERROR(IF(VLOOKUP(G18,playerlkp,3,0)=0,"",VLOOKUP(G18,playerlkp,3,0)),"") | L18: Tyreek Hill | M18: =IFERROR(IF(INDEX(Players,MATCH(L18,nickname,0),MATCH($C$1,Players!$1:$1,0))=0,"",INDEX(Players,MATCH(L18,nickname,0),MATCH($C$1,Players!$1:$1,0))),"") -> 9600 | N18: =IFERROR(IF(INDEX(Players,MATCH(L18,nickname,0),MATCH($D$1,Players!$1:$1,0))=0,"",INDEX(Players,MATCH(L18,nickname,0),MATCH($D$1,Players!$1:$1,0))),"") -> 19.505883 | O18: =IFERROR(IF(VLOOKUP(L18,playerlkp,3,0)=0,"",VLOOKUP(L18,playerlkp,3,0)),"")
A19: WR3 | C19: =IFERROR(IF(INDEX(Players,MATCH(B19,nickname,0),MATCH($C$1,Players!$1:$1,0))=0,"",INDEX(Players,MATCH(B19,nickname,0),MATCH($C$1,Players!$1:$1,0))),"") | D19: =IFERROR(IF(INDEX(Players,MATCH(B19,nickname,0),MATCH($D$1,Players!$1:$1,0))=0,"",INDEX(Players,MATCH(B19,nickname,0),MATCH($D$1,Players!$1:$1,0))),"") | E19: =IFERROR(IF(VLOOKUP(B19,playerlkp,3,0)=0,"",VLOOKUP(B19,playerlkp,3,0)),"") | H19: =IFERROR(IF(INDEX(Players,MATCH(G19,nickname,0),MATCH($C$1,Players!$1:$1,0))=0,"",INDEX(Players,MATCH(G19,nickname,0),MATCH($C$1,Players!$1:$1,0))),"") | I19: =IFERROR(IF(INDEX(Players,MATCH(G19,nickname,0),MATCH($D$1,Players!$1:$1,0))=0,"",INDEX(Players,MATCH(G19,nickname,0),MATCH($D$1,Players!$1:$1,0))),"") | J19: =IFERROR(IF(VLOOKUP(G19,playerlkp,3,0)=0,"",VLOOKUP(G19,playerlkp,3,0)),"") | L19: Tyreek Hill | M19: =IFERROR(IF(INDEX(Players,MATCH(L19,nickname,0),MATCH($C$1,Players!$1:$1,0))=0,"",INDEX(Players,MATCH(L19,nickname,0),MATCH($C$1,Players!$1:$1,0))),"") -> 9600 | N19: =IFERROR(IF(INDEX(Players,MATCH(L19,nickname,0),MATCH($D$1,Players!$1:$1,0))=0,"",INDEX(Players,MATCH(L19,nickname,0),MATCH($D$1,Players!$1:$1,0))),"") -> 19.505883 | O19: =IFERROR(IF(VLOOKUP(L19,playerlkp,3,0)=0,"",VLOOKUP(L19,playerlkp,3,0)),"")
A20: TE | C20: =IFERROR(IF(INDEX(Players,MATCH(B20,nickname,0),MATCH($C$1,Players!$1:$1,0))=0,"",INDEX(Players,MATCH(B20,nickname,0),MATCH($C$1,Players!$1:$1,0))),"") | D20: =IFERROR(IF(INDEX(Players,MATCH(B20,nickname,0),MATCH($D$1,Players!$1:$1,0))=0,"",INDEX(Players,MATCH(B20,nickname,0),MATCH($D$1,Players!$1:$1,0))),"") | E20: =IFERROR(IF(VLOOKUP(B20,playerlkp,3,0)=0,"",VLOOKUP(B20,playerlkp,3,0)),"") | H20: =IFERROR(IF(INDEX(Players,MATCH(G20,nickname,0),MATCH($C$1,Players!$1:$1,0))=0,"",INDEX(Players,MATCH(G20,nickname,0),MATCH($C$1,Players!$1:$1,0))),"") | I20: =IFERROR(IF(INDEX(Players,MATCH(G20,nickname,0),MATCH($D$1,Players!$1:$1,0))=0,"",INDEX(Players,MATCH(G20,nickname,0),MATCH($D$1,Players!$1:$1,0))),"") | J20: =IFERROR(IF(VLOOKUP(G20,playerlkp,3,0)=0,"",VLOOKUP(G20,playerlkp,3,0)),"") | L20: Sam LaPorta | M20: =IFERROR(IF(INDEX(Players,MATCH(L20,nickname,0),MATCH($C$1,Players!$1:$1,0))=0,"",INDEX(Players,MATCH(L20,nickname,0),MATCH($C$1,Players!$1:$1,0))),"") -> 8000 | N20: =IFERROR(IF(INDEX(Players,MATCH(L20,nickname,0),MATCH($D$1,Players!$1:$1,0))=0,"",INDEX(Players,MATCH(L20,nickname,0),MATCH($D$1,Players!$1:$1,0))),"") -> 11.52 | O20: =IFERROR(IF(VLOOKUP(L20,playerlkp,3,0)=0,"",VLOOKUP(L20,playerlkp,3,0)),"")
A21: FLEX | C21: =IFERROR(IF(INDEX(Players,MATCH(B21,nickname,0),MATCH($C$1,Players!$1:$1,0))=0,"",INDEX(Players,MATCH(B21,nickname,0),MATCH($C$1,Players!$1:$1,0))),"") | D21: =IFERROR(IF(INDEX(Players,MATCH(B21,nickname,0),MATCH($D$1,Players!$1:$1,0))=0,"",INDEX(Players,MATCH(B21,nickname,0),MATCH($D$1,Players!$1:$1,0))),"") | E21: =IFERROR(IF(VLOOKUP(B21,playerlkp,3,0)=0,"",VLOOKUP(B21,playerlkp,3,0)),"") | H21: =IFERROR(IF(INDEX(Players,MATCH(G21,nickname,0),MATCH($C$1,Players!$1:$1,0))=0,"",INDEX(Players,MATCH(G21,nickname,0),MATCH($C$1,Players!$1:$1,0))),"") | I21: =IFERROR(IF(INDEX(Players,MATCH(G21,nickname,0),MATCH($D$1,Players!$1:$1,0))=0,"",INDEX(Players,MATCH(G21,nickname,0),MATCH($D$1,Players!$1:$1,0))),"") | J21: =IFERROR(IF(VLOOKUP(G21,playerlkp,3,0)=0,"",VLOOKUP(G21,playerlkp,3,0)),"") | L21: Tyreek Hill | M21: =IFERROR(IF(INDEX(Players,MATCH(L21,nickname,0),MATCH($C$1,Players!$1:$1,0))=0,"",INDEX(Players,MATCH(L21,nickname,0),MATCH($C$1,Players!$1:$1,0))),"") -> 9600 | N21: =IFERROR(IF(INDEX(Players,MATCH(L21,nickname,0),MATCH($D$1,Players!$1:$1,0))=0,"",INDEX(Players,MATCH(L21,nickname,0),MATCH($D$1,Players!$1:$1,0))),"") -> 19.505883 | O21: =IFERROR(IF(VLOOKUP(L21,playerlkp,3,0)=0,"",VLOOKUP(L21,playerlkp,3,0)),"")
A22: DEF | C22: =IFERROR(IF(INDEX(Players,MATCH(B22,nickname,0),MATCH($C$1,Players!$1:$1,0))=0,"",INDEX(Players,MATCH(B22,nickname,0),MATCH($C$1,Players!$1:$1,0))),"") | D22: =IFERROR(IF(INDEX(Players,MATCH(B22,nickname,0),MATCH($D$1,Players!$1:$1,0))=0,"",INDEX(Players,MATCH(B22,nickname,0),MATCH($D$1,Players!$1:$1,0))),"") | E22: =IFERROR(IF(INDEX(Players,MATCH(B22,nickname,0),MATCH($E$1,Players!$1:$1,0))=0,"",INDEX(Players,MATCH(B22,nickname,0),MATCH($E$1,Players!$1:$1,0))), "") | H22: =IFERROR(IF(INDEX(Players,MATCH(G22,nickname,0),MATCH($C$1,Players!$1:$1,0))=0,"",INDEX(Players,MATCH(G22,nickname,0),MATCH($C$1,Players!$1:$1,0))),"") | I22: =IFERROR(IF(INDEX(Players,MATCH(G22,nickname,0),MATCH($D$1,Players!$1:$1,0))=0,"",INDEX(Players,MATCH(G22,nickname,0),MATCH($D$1,Players!$1:$1,0))),"") | J22: =IFERROR(IF(INDEX(Players,MATCH(G22,nickname,0),MATCH($E$1,Players!$1:$1,0))=0,"",INDEX(Players,MATCH(G22,nickname,0),MATCH($E$1,Players!$1:$1,0))), "") | L22: MIN | M22: =IFERROR(IF(INDEX(Players,MATCH(L22,nickname,0),MATCH($C$1,Players!$1:$1,0))=0,"",INDEX(Players,MATCH(L22,nickname,0),MATCH($C$1,Players!$1:$1,0))),"") -> 5000 | N22: =IFERROR(IF(INDEX(Players,MATCH(L22,nickname,0),MATCH($D$1,Players!$1:$1,0))=0,"",INDEX(Players,MATCH(L22,nickname,0),MATCH($D$1,Players!$1:$1,0))),"") -> 7.3529412 | O22: =IFERROR(IF(INDEX(Players,MATCH(L22,nickname,0),MATCH($E$1,Players!$1:$1,0))=0,"",INDEX(Players,MATCH(L22,nickname,0),MATCH($E$1,Players!$1:$1,0))), "")
A23: TOTALS | C23: =60000-SUM(C14:C22) -> 37500 | D23: =SUM(D14:D22) -> 45.232889 | H23: =60000-SUM(H14:H22) -> 26400 | I23: =SUM(I14:I22) -> 64.526248 | M23: =60000-SUM(M14:M22) -> -18200 | N23: =SUM(N14:N22) -> 147.45065

Sheet Players
A1: POSITION | B1: NICKNAME | C1: SALARY | D1: INJ | E1: AVG
A2: D | B2: MIN | C2: 5000 | E2: 7.3529412
A3: D | B3: TB | C3: 4900 | E3: 7.6315789
A4: D | B4: CIN | C4: 4800 | E4: 6.9411765
A5: D | B5: NO | C5: 4700 | E5: 8.4117647
A6: D | B6: BUF | C6: 4600 | E6: 8.8947368
A7: D | B7: DAL | C7: 4500 | E7: 9.6666667
A8: D | B8: SEA | C8: 4400 | E8: 6.4117647
A9: D | B9: PIT | C9: 4300 | E9: 8.1111111
A10: D | B10: MIA | C10: 4200 | E10: 8.6111111
A11: D | B11: CLE | C11: 4100 | E11: 8.7222222
A12: D | B12: CHI | C12: 4000 | E12: 7.0588235
A13: D | B13: LAC | C13: 4000 | E13: 6.5882353
... A40: QB | B40: Baker Mayfield | C40: 7200 | E40: 17.71579
A41: QB | B41: Caleb Williams | C41: 7100
A42: QB | B42: Deshaun Watson | C42: 7100 | E42: 12.971429
A43: QB | B43: Jayden Daniels | C43: 7000
A44: QB | B44: Derek Carr | C44: 7000 | E44: 14.654117
A45: QB | B45: Geno Smith | C45: 7000 | E45: 15.717333
A46: QB | B46: Will Levis | C46: 6900 | E46: 11.78
A47: QB | B47: Justin Fields | C47: 6900 | E47: 14.94875
A48: QB | B48: Russell Wilson | C48: 6900 | E48: 17.66
A49: QB | B49: Daniel Jones | C49: 6800 | E49: 10.493333
A50: QB | B50: Gardner Minshew II | C50: 6800 | E50: 12.825
A51: QB | B51: Aidan O'Connell | C51: 6800 | E51: 11.068334
A52: QB | B52: Sam Darnold | C52: 6700 | E52: 2.2163636
A53: QB | B53: Bryce Young | C53: 6700 | E53: 10.39875
A54: QB | B54: J.J. McCarthy | C54: 6700 | D54: IR
A55: QB | B55: Bo Nix | C55: 6600
A56: QB | B56: Jarrett Stidham | C56: 6600 | E56: 9.2133331
A57: QB | B57: Drake Maye | C57: 6500
A58: QB | B58: Jacoby Brissett | C58: 6500 | E58: 7.6200002
A59: QB | B59: Sam Howell | C59: 6200 | E59: 16.355295
A60: QB | B60: Jameis Winston | C60: 6100 | E60: 2.1371429
A61: QB | B61: Nathan Peterman | C61: 6000 | E61: -0.1
A62: QB | B62: Gavin Hardison | C62: 6000
A63: QB | B63: Chevan Cordeiro | C63: 6000
A64: QB | B64: Taylor Heinicke | C64: 6000 | E64: 14
A65: QB | B65: Trey Lance | C65: 6000 | E65: 0
A66: QB | B66: Shane Buechele | C66: 6000 | D66: IR
A67: QB | B67: Logan Woodside | C67: 6000 | E67: 0.34
A68: QB | B68: Desmond Ridder | C68: 6000 | E68: 11.79
A69: QB | B69: Jaren Hall | C69: 6000 | E69: 0.77999997
A70: QB | B70: Zach Wilson | C70: 6000 | E70: 10.578334
A71: QB | B71: Luis Perez | C71: 6000
A72: QB | B72: Sam Ehlinger | C72: 6000 | E72: 0
A73: QB | B73: Case Keenum | C73: 6000 | D73: IR | E73: 3.1849999
A74: QB | B74: Mac Jones | C74: 6000 | E74: 10.763637
A75: QB | B75: Mason Rudolph | C75: 6000 | E75: 8.1885714
A76: QB | B76: Teddy Bridgewater | C76: 6000 | E76: -0.1
A77: QB | B77: Nathan Rourke | C77: 6000
A78: QB | B78: Kedon Slovis | C78: 6000
A79: QB | B79: Tommy DeVito | C79: 6000 | E79: 10.726667
A80: QB | B80: Casey Bauman | C80: 6000
A81: QB | B81: Drew Lock | C81: 6000 | D81: Q | E81: 5.3533332
A82: QB | B82: Joe Flacco | C82: 6000 | E82: 20.736666
A83: QB | B83: Nick Mullens | C83: 6000 | E83: 14.948
A84: QB | B84: Marcus Mariota | C84: 6000 | D84: Q | E84: 4.2533334
A85: QB | B85: Clayton Tune | C85: 6000 | E85: 1.3542856
A86: QB | B86: Max Duggan | C86: 6000 | E86: 0
A87: QB | B87: Michael Penix Jr. | C87: 6000
A88: QB | B88: Rocky Lombardi | C88: 6000
A89: QB | B89: Jacob Sirmon | C89: 6000
A90: QB | B90: Jake Haener | C90: 6000 | E90: 0
A91: QB | B91: PJ Walker | C91: 6000 | E91: 4.1599998
A92: QB | B92: Carter Bradley | C92: 6000
A93: QB | B93: John Wolford | C93: 6000 | E93: 0
A94: QB | B94: Matt Barkley | C94: 6000 | E94: -0.30000001
A95: QB | B95: Spencer Rattler | C95: 6000
A96: QB | B96: John Paddock | C96: 6000
A97: QB | B97: Austin Reed | C97: 6000
A98: QB | B98: Nate Sudfeld | C98: 6000 | E98: -0.2
A99: QB | B99: Jack Plummer | C99: 6000
A100: QB | B100: Joe Milton III | C100: 6000
A101: QB | B101: Dresser Winn | C101: 6000 | E101: 0
A102: QB | B102: Jimmy Garoppolo | C102: 6000 | D102: IR | E102: 9.1374998
A103: QB | B103: C.J. Beathard | C103: 6000 | D103: Q | E103: 3.5766665
A104: QB | B104: Easton Stick | C104: 6000 | E104: 9.7942854
A105: QB | B105: Jake Browning | C105: 6000 | E105: 12.578334
A106: QB | B106: Tyson Bagent | C106: 6000 | E106: 11.852
A107: QB | B107: Ryan Tannehill | C107: 6000 | E107: 7.9127274
A108: QB | B108: Stetson Bennett | C108: 6000
A109: QB | B109: Davis Mills | C109: 6000 | E109: 2.2075
A110: QB | B110: Tim Boyle | C110: 6000 | E110: 3.7249999
A111: QB | B111: Sam Hartman | C111: 6000
A112: QB | B112: Jeff Driskel | C112: 6000 | E112: 7.9699998
A113: QB | B113: John Rhys Plumlee | C113: 6000
A114: QB | B114: Mike White | C114: 6000 | E114: 0.43714285
A115: QB | B115: Cooper Rush | C115: 6000 | E115: 0.53250003
A116: QB | B116: Skylar Thompson | C116: 6000 | E116: 0
A117: QB | B117: Kyle Trask | C117: 6000 | E117: -0.033333334
A118: QB | B118: Jake Luton | C118: 6000 | D118: Q
A119: QB | B119: Mitchell Trubisky | C119: 6000 | D119: Q | E119: 7.6685715
A120: QB | B120: Brett Rypien | C120: 6000 | E120: 2.8900001
A121: QB | B121: Dorian Thompson-Robinson | C121: 6000 | E121: 2.9
A122: QB | B122: Zack Annexstad | C122: 6000 | D122: Q
A123: QB | B123: Kyle Allen | C123: 6000 | E123: -0.18571428
A124: QB | B124: Andy Dalton | C124: 6000 | E124: 5.9099998
A125: QB | B125: Anthony Brown Jr. | C125: 6000 | E125: 3.79
A126: QB | B126: Hendon Hooker | C126: 6000
...

Sheet Player Lookup
A1: NICKNAME | B1: SALARY | C1: INJURY_IND | D1: PROJ_FPTS
A2: A.T. Perry | B2: 4200 | D2: 6.0666665
A3: Aaron Jones | B3: 6800 | D3: 12.815385
A4: Aaron Shampklin | B4: 4000
A5: Adam Prentice | B5: 4000 | D5: 0.46666666
A6: Adam Thielen | B6: 5400 | D6: 10.558824
A7: Adam Trautman | B7: 4100 | D7: 2.9058824
A8: Adonai Mitchell | B8: 5500
A9: Ahmarean Brown | B9: 4000
A10: Aidan O'Connell | B10: 6800 | D10: 11.068334
A11: Aidan Robbins | B11: 4000
A12: AJ Barner | B12: 4400
A13: Alec Holler | B13: 4000
A14: Alec Ingold | B14: 4400 | D14: 1.6727272
A15: Alec Pierce | B15: 5100 | D15: 4.6705883
A16: Alex Armah | B16: 4000 | D16: 0.69999999
A17: Alex Bachman | B17: 4000
A18: Alex Erickson | B18: 4000 | D18: 4.1333334
A19: Alexander Mattison | B19: 5200 | D19: 7.3874998
A20: Allen Robinson II | B20: 4100 | D20: 2.7764706
A21: Alvin Kamara | B21: 7100 | D21: 15.038462
A22: Amari Cooper | B22: 6600 | D22: 12.43125
A23: Ameer Abdullah | B23: 4900 | D23: 1.96875
A24: Amon-Ra St. Brown | B24: 8900 | D24: 16.631579
A25: Andre Baccellia | B25: 4000 | D25: 0
A26: Andrei Iosivas | B26: 4300 | D26: 4.7888887
A27: Andrew DePaola | B27: 4000 | D27: 0
A28: Andy Dalton | B28: 6000 | D28: 5.9099998
A29: Andy Isabella | B29: 4000 | D29: 0
A30: Anthony Brown Jr. | B30: 6000 | D30: 3.79
A31: Anthony Gould | B31: 4000
A32: Anthony Richardson | B32: 8300 | D32: 18.42
A33: Anthony Schwartz | B33: 4100 | C33: IR | D33: 2.7999999
A34: Antoine Green | B34: 4000 | C34: IR | D34: 0.23333333
A35: Antonio Gibson | B35: 5300 | D35: 6.4625001
A36: ARI | B36: 3000 | D36: 3.8235294
A37: Ashton Dulin | B37: 4100 | D37: 5
A38: ATL | B38: 3600 | D38: 5.8235294
A39: Audric Estime | B39: 4800
A40: Austin Ekeler | B40: 5900 | D40: 11.421428
A41: Austin Hooper | B41: 4500 | D41: 2.2437501
A42: Austin Jones | B42: 4000
A43: Austin Mack | B43: 4100
A44: Austin Reed | B44: 6000
A45: Austin Stogner | B45: 4000
A46: Austin Trammell | B46: 4000 | D46: 0.20714286
A47: Austin Walter | B47: 4000 | C47: Q
A48: Avery Williams | B48: 4000 | D48: 1.6176471
A49: Ayir Asante | B49: 4000
A50: Baker Mayfield | B50: 7200 | D50: 17.71579
A51: Ben Mason | B51: 4000 | C51: Q
A52: Ben Sinnott | B52: 4400
A53: Ben Skowronek | B53: 4000 | D53: 1.85
A54: Bernhard Raimann | B54: 4000 | D54: 0
A55: Bernhard Seikovits | B55: 4000
A56: Bijan Robinson | B56: 8800 | D56: 12.782353
A57: Blake Corum | B57: 5400
A58: Blake Lynch | B58: 4000
A59: Blake Watson | B59: 4000
A60: Blake Whiteheart | B60: 4000 | D60: 0
A61: Bo Nix | B61: 6600
A62: Boston Scott | B62: 4700 | C62: O | D62: 0.9857143
A63: Brady Russell | B63: 4200 | D63: 0
A64: Brandin Cooks | B64: 5300 | D64: 9.0882353
A65: Brandon Bolden | B65: 4000 | D65: 2.2200001
A66: Brandon Dillon | B66: 4000 | C66: Q
A67: Brandon Johnson | B67: 4100 | D67: 6.3900002
A68: Brandon Powell | B68: 4300 | D68: 3.0941176
A69: Braxton Berrios | B69: 4100 | D69: 2.6117648
A70: Braylon Sanders | B70: 4000 | C70: Q | D70: 0.34999999
A71: Brenden Rice | B71: 4000
A72: Brenton Strange | B72: 4300 | D72: 2.4
A73: Brett Rypien | B73: 6000 | D73: 2.8900001
A74: Brevin Easton | B74: 4000
A75: Brevin Jordan | B75: 4200 | D75: 4.3461538
A76: Brevyn Spann-Ford | B76: 4000
A77: Brian Robinson Jr. | B77: 5900 | D77: 12.006667
A78: Brian Thomas Jr. | B78: 5100
A79: British Brooks | B79: 4000
A80: Brittain Brown | B80: 4000
A81: Brock Bowers | B81: 5400 | C81: Q
A82: Brock Wright | B82: 4300 | D82: 2.5
A83: Bryan Thompson | B83: 4100 | C83: Q
A84: Bryce Ford-Wheaton | B84: 4000
A85: Bryce Oliver | B85: 4000
A86: Bryce Young | B86: 6700 | D86: 10.39875
A87: Brycen Hopkins | B87: 4000 | D87: 2.06
A88: Brycen Tremayne | B88: 4000
A89: Bub Means | B89: 4000
A90: Bucky Irving | B90: 5000
A91: BUF | B91: 4600 | D91: 8.8947368
A92: Byron Pringle | B92: 4100 | D92: 1.623077
A93: C.J. Beathard | B93: 6000 | C93: Q | D93: 3.5766665
A94: C.J. Goodwin | B94: 4000
A95: C.J. Ham | B95: 4000 | D95: 0.83749998
A96: C.J. Stroud | B96: 8500 | D96: 18.322354
A97: Cade Otton | B97: 5200 | D97: 6.7166668
A98: Cade Stover | B98: 4200
A99: Cal Adomitis | B99: 4000 | D99: 0
A100: Caleb Williams | B100: 7100
...

Sheet Sheet1
B1: POSITION | C1: NICKNAME | D1: SALARY | E1: INJURY_IND | F1: PROJ_FPTS
B2: WR | C2: A.J. Brown | D2: 8200 | F2: 14
B3: RB | C3: Adam Prentice | D3: 4200 | E3: Q | F3: 0.6
B4: WR | C4: Adam Thielen | D4: 7400 | F4: 11.2
B5: QB | C5: Aidan O'Connell | D5: 6300 | F5: 0
B6: RB | C6: Alec Ingold | D6: 4200 | E6: Q | F6: 0.6
B7: WR | C7: Alec Pierce | D7: 5100 | F7: 4.6
B8: RB | C8: Alexander Mattison | D8: 6900 | F8: 12.4
B9: WR | C9: Allen Lazard | D9: 5500 | F9: 5.8
B10: RB | C10: Alvin Kamara | D10: 7500 | F10: 13.7
B11: WR | C11: Amari Cooper | D11: 6600 | F11: 11.3
B12: RB | C12: Ameer Abdullah | D12: 5200 | F12: 2.4
B13: WR | C13: Amon-Ra St. Brown | D13: 7800 | E13: Q | F13: 5.4
B14: WR | C14: Andrei Iosivas | D14: 4300 | F14: 2.4
B15: QB | C15: Andy Dalton | D15: 6200 | F15: 0
B16: RB | C16: Antonio Gibson | D16: 5100 | F16: 6.3
B17: D | C17: ARI | D17: 3300 | F17: 5.6
B18: D | C18: ATL | D18: 4100 | F18: 6.2
B19: TE | C19: Austin Hooper | D19: 4800 | F19: 2
B20: QB | C20: Bailey Zappe | D20: 6400 | F20: 9
B21: QB | C21: Baker Mayfield | D21: 7100 | F21: 15.8
B22: RB | C22: Bijan Robinson | D22: 7600 | F22: 16.7
B23: RB | C23: Boston Scott | D23: 4500 | F23: 1.4
B24: WR | C24: Brandon Aiyuk | D24: 7700 | F24: 13.1
B25: WR | C25: Brandon Powell | D25: 5100 | F25: 3.3
... B68: WR | C68: Deebo Samuel | D68: 7200 | F68: 11.5
B69: WR | C69: Demario Douglas | D69: 4700 | E69: Q | F69: 3.8
B70: QB | C70: Derek Carr | D70: 6600 | F70: 15.6
B71: RB | C71: D'Ernest Johnson | D71: 4200 | F71: 1.3
B72: QB | C72: Deshaun Watson | D72: 7000 | E72: Q | F72: 16.2
B73: QB | C73: Desmond Ridder | D73: 6800 | F73: 14.8
B74: D | C74: DET | D74: 4400 | F74: 6.8
B75: WR | C75: DeVante Parker | D75: 5200 | F75: 6.6
B76: WR | C76: Deven Thompkins | D76: 4700 | F76: 2.4
B77: RB | C77: Devin Singletary | D77: 4700 | F77: 4.5
B78: WR | C78: DeVonta Smith | D78: 7300 | F78: 11.9
B79: WR | C79: DJ Chark Jr. | D79: 6000 | F79: 7.2
B80: WR | C80: DJ Moore | D80: 8000 | F80: 12.5
B81: WR | C81: DK Metcalf | D81: 7500 | F81: 12.2
B82: WR | C82: Donovan Peoples-Jones | D82: 5200 | F82: 3.6
B83: RB | C83: D'Onta Foreman | D83: 6000 | F83: 7.8
B84: WR | C84: Drake London | D84: 6400 | F84: 9.4
... B88: RB | C88: Emari Demercado | D88: 5900 | F88: 9.1
B89: WR | C89: Equanimeous St. Brown | D89: 4600 | E89: Q | F89: 2.8
B90: TE | C90: Evan Engram | D90: 5500 | F90: 8.2
B91: RB | C91: Ezekiel Elliott | D91: 5400 | F91: 7.2
B92: TE | C92: Foster Moreau | D92: 4600 | F92: 3
B93: QB | C93: Gardner Minshew II | D93: 6500 | F93: 16
B94: WR | C94: Garrett Wilson | D94: 6900 | F94: 11.1
B95: QB | C95: Geno Smith | D95: 6800 | E95: Q | F95: 17
B96: TE | C96: George Kittle | D96: 5900 | F96: 8.2
B97: TE | C97: Harrison Bryant | D97: 4400 | F97: 1.5
B98: TE | C98: Hayden Hurst | D98: 4900 | F98: 5.5
B99: D | C99: HOU | D99: 3700 | F99: 6.2
B100: TE | C100: Hunter Henry | D100: 5600 | F100: 6
B101: WR | C101: Hunter Renfrow | D101: 5300 | F101: 4.1
B102: D | C102: IND | D102: 3700 | F102: 5.6
B103: TE | C103: Irv Smith Jr. | D103: 4500 | F103: 3.7
B104: WR | C104: Isaiah McKenzie | D104: 4300 | F104: 1.6
B105: D | C105: JAC | D105: 4500 | F105: 6.5
B106: WR | C106: Jahan Dotson | D106: 5700 | F106: 8.1
B107: RB | C107: Jahmyr Gibbs | D107: 5800 | E107: Q | F107: 5.8
B108: WR | C108: Jake Bobo | D108: 4400 | F108: 1.2
B109: RB | C109: Jakob Johnson | D109: 4000 | F109: 0.4
B110: WR | C110: Jakobi Meyers | D110: 6700 | F110: 10
B111: QB | C111: Jalen Hurts | D111: 8700 | F111: 22.2
B112: WR | C112: Jamal Agnew | D112: 4500 | F112: 1.7
B113: WR | C113: Ja'Marr Chase | D113: 9300 | F113: 16.7
B114: QB | C114: Jameis Winston | D114: 6200 | F114: 6.9
B115: WR | C115: Jameson Williams | D115: 5500 | F115: 4.9
B116: RB | C116: JaMycal Hasty | D116: 4100 | F116: 0.9
B117: QB | C117: Jared Goff | D117: 7800 | F117: 17.4
B118: WR | C118: Jauan Jennings | D118: 5100 | F118: 2.8
B119: WR | C119: Jaxon Smith-Njigba | D119: 4800 | F119: 7
... B138: QB | C138: Joshua Dobbs | D138: 6700 | F138: 16.1
B139: WR | C139: JuJu Smith-Schuster | D139: 5300 | E139: Q | F139: 4.1
B140: QB | C140: Justin Fields | D140: 8500 | F140: 19.7
B141: WR | C141: K.J. Osborn | D141: 6200 | F141: 8
B142: WR | C142: Kalif Raymond | D142: 5100 | F142: 5.6
B143: RB | C143: Kareem Hunt | D143: 5400 | F143: 4.3
B144: RB | C144: Keaontay Ingram | D144: 5600 | E144: Q | F144: 1.7
B145: RB | C145: Kendre Miller | D145: 4700 | F145: 5.8
B146: WR | C146: Kendrick Bourne | D146: 5700 | F146: 6.7
B147: RB | C147: Kenneth Gainwell | D147: 5000 | F147: 6.4
B148: RB | C148: Kenneth Walker III | D148: 8400 | F148: 15.7
B149: RB | C149: Ke'Shawn Vaughn | D149: 4500 | F149: 0.9
B150: WR | C150: KhaDarel Hodge | D150: 4700 | F150: 1.9
B151: RB | C151: Khari Blasingame | D151: 4500 | F151: 0.9
B152: QB | C152: Kirk Cousins | D152: 8000 | F152: 19
B153: RB | C153: Kyle Juszczyk | D153: 4100 | F153: 1.8
B154: TE | C154: Kyle Pitts | D154: 5300 | F154: 6.9
B155: TE | C155: Kylen Granson | D155: 4600 | F155: 4.2
B156: RB | C156: Kyren Williams | D156: 8200 | F156: 14.7
... B172: RB | C172: Mike Boone | D172: 4200 | F172: 1.3
B173: WR | C173: Mike Evans | D173: 7600 | E173: Q | F173: 11.4
B174: TE | C174: Mike Gesicki | D174: 4700 | F174: 4.1
B175: RB | C175: Miles Sanders | D175: 5900 | F175: 10.5
B176: D | C176: MIN | D176: 4000 | F176: 6.2
B177: TE | C177: Mo Alie-Cox | D177: 4500 | E177: Q | F177: 1.3
B178: D | C178: NE | D178: 3600 | F178: 6.4
...

Sheet DEF
A1: POSITION | B1: NICKNAME | C1: SALARY | D1: INJ | E1: AVG
A2: D | B2: MIN | C2: 5000 | E2: 7.3529412
A3: D | B3: TB | C3: 4900 | E3: 7.6315789
A4: D | B4: CIN | C4: 4800 | E4: 6.9411765
A5: D | B5: NO | C5: 4700 | E5: 8.4117647
A6: D | B6: BUF | C6: 4600 | E6: 8.8947368 | F6: 8.8947368
A7: D | B7: DAL | C7: 4500 | E7: 9.6666667 | F7: 9.6666667
A8: D | B8: SEA | C8: 4400 | E8: 6.4117647
A9: D | B9: PIT | C9: 4300 | E9: 8.1111111
A10: D | B10: MIA | C10: 4200 | E10: 8.6111111
A11: D | B11: CLE | C11: 4100 | E11: 8.7222222 | F11: 8.7222222
A12: D | B12: CHI | C12: 4000 | E12: 7.0588235
A13: D | B13: LAC | C13: 4000 | E13: 6.5882353
A14: D | B14: DET | C14: 3900 | E14: 6.1
A15: D | B15: HOU | C15: 3900 | E15: 8.4210526
A16: D | B16: LV | C16: 3800 | E16: 8.5882353
A17: D | B17: NYG | C17: 3800 | E17: 7.7058824
A18: D | B18: TEN | C18: 3700 | E18: 6
A19: D | B19: JAC | C19: 3700 | E19: 7.2352941
A20: D | B20: ATL | C20: 3600 | E20: 5.8235294
A21: D | B21: IND | C21: 3500 | E21: 8.2352941
A22: D | B22: DEN | C22: 3400 | E22: 6.9411765
A23: D | B23: WAS | C23: 3400 | E23: 3.4117647
... A27: D | B27: ARI | C27: 3000 | E27: 3.8235294

Sheet QB
A1: POSITION | B1: NICKNAME | C1: SALARY | D1: INJ | E1: AVG
A2: QB | B2: Josh Allen | C2: 9200 | E2: 24.989473 | F2: 24.989473
A3: QB | B3: C.J. Stroud | C3: 8500 | E3: 18.322354
A4: QB | B4: Joe Burrow | C4: 8400 | E4: 15.316
A5: QB | B5: Anthony Richardson | C5: 8300 | E5: 18.42
A6: QB | B6: Kyler Murray | C6: 7900 | E6: 18.92
A7: QB | B7: Dak Prescott | C7: 7800 | E7: 21.358888
A8: QB | B8: Tua Tagovailoa | C8: 7700 | E8: 16.545556
A9: QB | B9: Justin Herbert | C9: 7600 | E9: 18.512308 | F9: 18.512308
A10: QB | B10: Kirk Cousins | C10: 7500 | E10: 19.342501
A11: QB | B11: Jared Goff | C11: 7500 | E11: 17.544
A12: QB | B12: Trevor Lawrence | C12: 7400 | E12: 17.283751
A13: QB | B13: Matthew Stafford | C13: 7300 | E13: 16.281176
A14: QB | B14: Baker Mayfield | C14: 7200 | E14: 17.71579 | F14: 17.71579
A15: QB | B15: Deshaun Watson | C15: 7100 | E15: 12.971429
A16: QB | B16: Caleb Williams | C16: 7100
A17: QB | B17: Geno Smith | C17: 7000 | E17: 15.717333
A18: QB | B18: Derek Carr | C18: 7000 | E18: 14.654117
A19: QB | B19: Jayden Daniels | C19: 7000
A20: QB | B20: Russell Wilson | C20: 6900 | E20: 17.66
A21: QB | B21: Will Levis | C21: 6900 | E21: 11.78
A22: QB | B22: Gardner Minshew II | C22: 6800 | E22: 12.825
A23: QB | B23: Daniel Jones | C23: 6800 | E23: 10.493333
A24: QB | B24: Bryce Young | C24: 6700 | E24: 10.39875
A25: QB | B25: Sam Darnold | C25: 6700 | E25: 2.2163636
A26: QB | B26: Bo Nix | C26: 6600
A27: QB | B27: Jacoby Brissett | C27: 6500 | E27: 7.6200002
D126: Q
D144: Q
D146: Q
D154: Q
D172: Q
D175: Q
D187: Q
D204: Q
D212: Q

Sheet RB
A1: POSITION | B1: NICKNAME | C1: SALARY | D1: INJ | E1: AVG
A2: RB | B2: Bijan Robinson | C2: 8800 | E2: 12.782353
A3: RB | B3: Jonathan Taylor | C3: 8600 | E3: 14.689999
A4: RB2 | B4: Jahmyr Gibbs | C4: 8000 | E4: 14.522222
A5: RB | B5: Kyren Williams | C5: 7800 | E5: 18.961538
A6: RB | B6: Rachaad White | C6: 7700 | E6: 13.736842
A7: RB | B7: James Cook | C7: 7600 | E7: 12.173684
A8: RB | B8: Travis Etienne Jr. | C8: 7500 | E8: 14.905882
A9: RB | B9: Kenneth Walker III | C9: 7400 | E9: 12.326666
A10: RB | B10: Joe Mixon | C10: 7300 | E10: 14.176471
A11: RB2 | B11: De'Von Achane | C11: 7200 | E11: 15.141666
A12: RB | B12: Alvin Kamara | C12: 7100 | E12: 15.038462
A13: RB1 | B13: David Montgomery | C13: 7000 | E13: 13.166667
... A29: RB | B29: Chuba Hubbard | C29: 5600 | E29: 9.5882353

Sheet WR
A1: POSITION | B1: NICKNAME | C1: SALARY | D1: INJ | E1: AVG
A2: WR1 | B2: Tyreek Hill | C2: 9600 | E2: 19.505883
A3: WR1 | B3: Ja'Marr Chase | C3: 9100 | E3: 13.295
A4: WR1 | B4: Justin Jefferson | C4: 9000 | E4: 16.82
A5: WR1 | B5: Amon-Ra St. Brown | C5: 8900 | E5: 16.631579
A6: WR2 | B6: Puka Nacua | C6: 8400 | E6: 15.244444
A7: WR1 | B7: Mike Evans | C7: 7900 | E7: 14.421053
A8: WR1 | B8: Davante Adams | C8: 7500 | E8: 12.582353
A9: WR2 | B9: Jaylen Waddle | C9: 7200 | E9: 11.173334
A10: WR2 | B10: Nico Collins | C10: 7100 | E10: 13.816666
A11: WR1 | B11: Chris Olave | C11: 7000 | E11: 11.7375
A12: WR1 | B12: Cooper Kupp | C12: 7000 | E12: 10.776924
A13: WR1 | B13: DJ Moore | C13: 6900 | E13: 14.029412
... A18: WR1 | B18: Amari Cooper | C18: 6600 | E18: 12.43125
A19: WR1 | B19: Marvin Harrison Jr. | C19: 6600
A20: WR1 | B20: Michael Pittman Jr. | C20: 6500 | E20: 12.23125
A21: WR1 | B21: George Pickens | C21: 6500 | E21: 10.238889
A22: WR1 | B22: Malik Nabers | C22: 6300
A23: WR | B23: Calvin Ridley | C23: 6200 | E23: 11.288235
A24: WR1 | B24: Terry McLaurin | C24: 6200 | E24: 9.9823528
A25: WR1 | B25: Christian Kirk | C25: 6100 | E25: 10.146667
A26: WR2 | B26: Gabe Davis | C26: 6100 | E26: 8.6812496
A27: WR2 | B27: Keon Coleman | C27: 6000
A28: WR2 | B28: Jameson Williams | C28: 5800 | E28: 6.3600001
A29: WR2 | B29: Rome Odunze | C29: 5800
A30: WR2 | B30: Jerry Jeudy | C30: 5700 | E30: 7.1750002
A31: WR1 | B31: Diontae Johnson | C31: 5600 | E31: 10
A32: WR2 | B32: Chris Godwin | C32: 5600 | E32: 9.7999998
A33: WR1 | B33: Courtland Sutton | C33: 5500 | E33: 10.04375
A34: WR2 | B34: Adonai Mitchell | C34: 5500
A35: WR2 | B35: Adam Thielen | C35: 5400 | E35: 10.558824
A36: WR1 | B36: Khalil Shakir | C36: 5400 | E36: 6.561111
A37: WR1 | B37: Brandin Cooks | C37: 5300 | E37: 9.0882353
A38: WR2 | B38: Ladd McConkey | C38: 5300
A39: WR2 | B39: Rashid Shaheed | C39: 5200 | E39: 8.8400004
A40: WR2 | B40: Jaxon Smith-Njigba | C40: 5200 | E40: 6.9588237
A41: WR2 | B41: Jakobi Meyers | C41: 5100 | E41: 11.4425
A42: WR1 | B42: Joshua Palmer | C42: 5000 | E42: 8.7699997
A43: WR2 | B43: Van Jefferson | C43: 5000 | E43: 2.2357142
A44: WR | B44: Tyler Boyd | C44: 4900 | E44: 6.6058825
A45: WR2 | B45: Josh Reynolds | C45: 4800 | E45: 6.9473684
A46: WR2 | B46: Darnell Mooney | C46: 4800 | E46: 4.5285715
A47: WR2 | B47: Ja'Lynn Polk | C47: 4800
A48: WR2 | B48: Wan'Dale Robinson | C48: 4700 | E48: 6.8799998
A49: WR2 | B49: Jalen Tolbert | C49: 4700 | E49: 3.1866666
A50: WR2 | B50: Michael Wilson | C50: 4500 | E50: 6.8214286
A51: WR | B51: Treylon Burks | C51: 4500 | E51: 3.19
A52: WR2 | B52: Olamide Zaccheaus | C52: 4400 | E52: 2.8666668
A53: WR2 | B53: Brandon Powell | C53: 4300 | E53: 3.0941176
A54: WR1 | B54: DeMario Douglas | C54: 4000 | E54: 5.9071426

Sheet TE
A1: POSITION | B1: NICKNAME | C1: SALARY | D1: INJ | E1: AVG
A2: TE | B2: Sam LaPorta | C2: 8000 | E2: 11.52 | F2: 11.52
A3: TE | B3: Dalton Kincaid | C3: 6800 | E3: 7.4555554
A4: TE | B4: Trey McBride | C4: 6400 | E4: 8.2941176
A5: TE | B5: Evan Engram | C5: 6200 | E5: 10.194118 | F5: 10.194118
A6: TE | B6: Jake Ferguson | C6: 6000 | E6: 9.6611108
A7: TE | B7: David Njoku | C7: 5900 | E7: 10.205882 | F7: 10.205882
A8: TE | B8: Pat Freiermuth | C8: 5300 | E8: 5.9083335
A9: TE | B9: Cade Otton | C9: 5200 | E9: 6.7166668
A10: TE | B10: Cole Kmet | C10: 5100 | E10: 9.0375004
A11: TE | B11: Daniel Bellinger | C11: 5000 | E11: 2.9230769
A12: TE | B12: Mike Gesicki | C12: 4900 | E12: 3.3933334
A13: TE | B13: Michael Mayer | C13: 4900 | E13: 4.8250001
A14: TE | B14: Hunter Henry | C14: 4900 | E14: 7.6076924
A15: TE | B15: Chig Okonkwo | C15: 4800 | E15: 5.082353
A16: TE | B16: Zach Ertz | C16: 4800 | E16: 5.457143
A17: TE | B17: Kylen Granson | C17: 4700 | E17: 3.8666667
A18: TE | B18: Colby Parkinson | C18: 4700 | E18: 3.2800001
A19: TE | B19: Juwan Johnson | C19: 4700 | E19: 6.1000002
A20: TE | B20: Jonnu Smith | C20: 4600 | E20: 6.6133331
A21: TE | B21: Ja'Tavion Sanders | C21: 4500
A22: TE | B22: Will Dissly | C22: 4300 | E22: 2.4384616
A23: TE | B23: Josh Oliver | C23: 4300 | E23: 3.2538461
A24: TE | B24: Charlie Woerner | C24: 4200 | E24: 0.93999996
A25: TE | B25: Brady Russell | C25: 4200 | E25: 0
A26: TE | B26: Adam Trautman | C26: 4100 | E26: 2.9058824

Sheet FLEX
A1: POSITION | B1: NICKNAME | C1: SALARY | D1: INJ | E1: AVG
A2: FLEX | B2: Bijan Robinson | C2: 8800 | E2: 12.782353
A3: FLEX | B3: Jonathan Taylor | C3: 8600 | E3: 14.689999
A4: FLEX | B4: Jahmyr Gibbs | C4: 8000 | E4: 14.522222
A5: FLEX | B5: Kyren Williams | C5: 7800 | E5: 18.961538
A6: FLEX | B6: Rachaad White | C6: 7700 | E6: 13.736842
A7: FLEX | B7: James Cook | C7: 7600 | E7: 12.173684
A8: FLEX | B8: Travis Etienne Jr. | C8: 7500 | E8: 14.905882
A9: FLEX | B9: Kenneth Walker III | C9: 7400 | E9: 12.326666
A10: FLEX | B10: Joe Mixon | C10: 7300 | E10: 14.176471
A11: FLEX | B11: De'Von Achane | C11: 7200 | E11: 15.141666
A12: FLEX | B12: Alvin Kamara | C12: 7100 | E12: 15.038462
A13: FLEX | B13: David Montgomery | C13: 7000 | E13: 13.166667
... A29: FLEX | B29: Chuba Hubbard | C29: 5600 | E29: 9.5882353
